pyelw/__init__.py
pyelw/elw.py
pyelw/fracdiff.py
pyelw/lw.py
pyelw/lw_bootstrap_m.py
pyelw/optimization.py
pyelw/simulate.py
pyelw/twostep.py
pyelw-0.9.5.dist-info/licenses/LICENSE
pyelw-0.9.5.dist-info/METADATA
pyelw-0.9.5.dist-info/WHEEL
pyelw-0.9.5.dist-info/top_level.txt
pyelw-0.9.5.dist-info/RECORD
