Metadata-Version: 2.4
Name: pyelw
Version: 0.9.5
Summary: Exact Local Whittle Estimation for Long Memory Time Series
Author-email: "Jason R. Blevins" <blevins.141@osu.edu>
License: BSD-3-Clause
Project-URL: Homepage, https://github.com/jrblevin/pyelw
Project-URL: Repository, https://github.com/jrblevin/pyelw.git
Project-URL: Documentation, https://github.com/jrblevin/pyelw#readme
Project-URL: Bug Tracker, https://github.com/jrblevin/pyelw/issues
Keywords: fractional integration,long memory,exact local Whittle estimation,ARFIMA,econometrics,time-series
Classifier: Intended Audience :: Science/Research
Classifier: Programming Language :: Python :: 3
Classifier: Programming Language :: Python :: 3.9
Classifier: Programming Language :: Python :: 3.10
Classifier: Programming Language :: Python :: 3.11
Classifier: Programming Language :: Python :: 3.12
Classifier: Programming Language :: Python :: 3.13
Classifier: License :: OSI Approved :: BSD License
Classifier: Operating System :: OS Independent
Classifier: Topic :: Scientific/Engineering :: Mathematics
Classifier: Topic :: Scientific/Engineering :: Information Analysis
Requires-Python: >=3.9
License-File: LICENSE
Requires-Dist: numpy
Provides-Extra: test
Requires-Dist: pytest~=8.4.1; extra == "test"
Requires-Dist: scipy>=1.13.1; extra == "test"
Requires-Dist: pandas>=2.2.0; extra == "test"
Requires-Dist: pandas-datareader~=0.10.0; extra == "test"
Provides-Extra: dev
Requires-Dist: pytest~=8.4.1; extra == "dev"
Requires-Dist: scipy>=1.13.1; extra == "dev"
Requires-Dist: pandas>=2.2.0; extra == "dev"
Requires-Dist: pandas-datareader~=0.10.0; extra == "dev"
Dynamic: license-file
